{"7": [["5-7", "5-8", "5-9", "5-10", "5-11", "5-12", "5-13"], [{"name": "Pos", "value": ["Nan", "Nan", "Nan", "Nan", "Nan", "Nan", 0.0]}, {"name": "Neu", "value": ["Nan", "Nan", "Nan", "Nan", "Nan", "Nan", 50.0]}, {"name": "Neg", "value": ["Nan", "Nan", "Nan", "Nan", "Nan", "Nan", 50.0]}]], "8": [["5-7", "5-8", "5-9", "5-10", "5-11", "5-12", "5-13"], [{"name": "Pos", "value": ["Nan", "Nan", "Nan", "Nan", "Nan", "Nan", 0.0]}, {"name": "Neu", "value": ["Nan", "Nan", "Nan", "Nan", "Nan", "Nan", 50.0]}, {"name": "Neg", "value": ["Nan", "Nan", "Nan", "Nan", "Nan", "Nan", 50.0]}]], "9": [["5-7", "5-8", "5-9", "5-10", "5-11", "5-12", "5-13"], [{"name": "Pos", "value": ["Nan", "Nan", "Nan", "Nan", "Nan", "Nan", 0.0]}, {"name": "Neu", "value": ["Nan", "Nan", "Nan", "Nan", "Nan", "Nan", 50.0]}, {"name": "Neg", "value": ["Nan", "Nan", "Nan", "Nan", "Nan", "Nan", 50.0]}]], "10": [["5-7", "5-8", "5-9", "5-10", "5-11", "5-12", "5-13"], [{"name": "Pos", "value": ["Nan", "Nan", "Nan", "Nan", "Nan", "Nan", 0.0]}, {"name": "Neu", "value": ["Nan", "Nan", "Nan", "Nan", "Nan", "Nan", 50.0]}, {"name": "Neg", "value": ["Nan", "Nan", "Nan", "Nan", "Nan", "Nan", 50.0]}]], "11": [["5-8", "5-9", "5-10", "5-11", "5-12", "5-13", "5-14"], [{"name": "Pos", "value": ["Nan", "Nan", "Nan", "Nan", "Nan", 0.0, "Nan"]}, {"name": "Neu", "value": ["Nan", "Nan", "Nan", "Nan", "Nan", 50.0, "Nan"]}, {"name": "Neg", "value": ["Nan", "Nan", "Nan", "Nan", "Nan", 50.0, "Nan"]}]], "12": [["5-9", "5-10", "5-11", "5-12", "5-13", "5-14", "5-15"], [{"name": "Pos", "value": ["Nan", "Nan", "Nan", "Nan", 0.0, "Nan", "Nan"]}, {"name": "Neu", "value": ["Nan", "Nan", "Nan", "Nan", 50.0, "Nan", "Nan"]}, {"name": "Neg", "value": ["Nan", "Nan", "Nan", "Nan", 50.0, "Nan", "Nan"]}]], "13": [["5-10", "5-11", "5-12", "5-13", "5-14", "5-15", "5-16"], [{"name": "Pos", "value": ["Nan", "Nan", "Nan", 0.0, "Nan", "Nan", 0.0]}, {"name": "Neu", "value": ["Nan", "Nan", "Nan", 50.0, "Nan", "Nan", 100.0]}, {"name": "Neg", "value": ["Nan", "Nan", "Nan", 50.0, "Nan", "Nan", 0.0]}]], "14": [["5-11", "5-12", "5-13", "5-14", "5-15", "5-16", "5-17"], [{"name": "Pos", "value": ["Nan", "Nan", 0.0, "Nan", "Nan", 0.0, 0.0]}, {"name": "Neu", "value": ["Nan", "Nan", 50.0, "Nan", "Nan", 100.0, 100.0]}, {"name": "Neg", "value": ["Nan", "Nan", 50.0, "Nan", "Nan", 0.0, 0.0]}]], "15": [["5-12", "5-13", "5-14", "5-15", "5-16", "5-17", "5-18"], [{"name": "Pos", "value": ["Nan", 0.0, "Nan", "Nan", 0.0, 0.0, 0.0]}, {"name": "Neu", "value": ["Nan", 50.0, "Nan", "Nan", 100.0, 100.0, 100.0]}, {"name": "Neg", "value": ["Nan", 50.0, "Nan", "Nan", 0.0, 0.0, 0.0]}]], "16": [["5-13", "5-14", "5-15", "5-16", "5-17", "5-18", "5-19"], [{"name": "Pos", "value": [0.0, "Nan", "Nan", 0.0, 0.0, 0.0, 75.0]}, {"name": "Neu", "value": [50.0, "Nan", "Nan", 100.0, 100.0, 100.0, 25.0]}, {"name": "Neg", "value": [50.0, "Nan", "Nan", 0.0, 0.0, 0.0, 0.0]}]], "17": [["5-14", "5-15", "5-16", "5-17", "5-18", "5-19", "5-20"], [{"name": "Pos", "value": ["Nan", "Nan", 0.0, 0.0, 0.0, 75.0, 0.0]}, {"name": "Neu", "value": ["Nan", "Nan", 100.0, 100.0, 100.0, 25.0, 71.42857142857143]}, {"name": "Neg", "value": ["Nan", "Nan", 0.0, 0.0, 0.0, 0.0, 28.571428571428573]}]], "18": [["5-15", "5-16", "5-17", "5-18", "5-19", "5-20", "5-21"], [{"name": "Pos", "value": ["Nan", 0.0, 0.0, 0.0, 75.0, 0.0, 16.666666666666668]}, {"name": "Neu", "value": ["Nan", 100.0, 100.0, 100.0, 25.0, 71.42857142857143, 66.66666666666667]}, {"name": "Neg", "value": ["Nan", 0.0, 0.0, 0.0, 0.0, 28.571428571428573, 16.666666666666668]}]], "19": [["5-16", "5-17", "5-18", "5-19", "5-20", "5-21", "5-22"], [{"name": "Pos", "value": [0.0, 0.0, 0.0, 75.0, 0.0, 16.666666666666668, 11.11111111111111]}, {"name": "Neu", "value": [100.0, 100.0, 100.0, 25.0, 71.42857142857143, 66.66666666666667, 88.88888888888889]}, {"name": "Neg", "value": [0.0, 0.0, 0.0, 0.0, 28.571428571428573, 16.666666666666668, 0.0]}]], "20": [["5-17", "5-18", "5-19", "5-20", "5-21", "5-22", "5-23"], [{"name": "Pos", "value": [0.0, 0.0, 75.0, 0.0, 16.666666666666668, 11.11111111111111, 0.0]}, {"name": "Neu", "value": [100.0, 100.0, 25.0, 71.42857142857143, 66.66666666666667, 88.88888888888889, 89.28571428571429]}, {"name": "Neg", "value": [0.0, 0.0, 0.0, 28.571428571428573, 16.666666666666668, 0.0, 10.714285714285714]}]], "21": [["5-18", "5-19", "5-20", "5-21", "5-22", "5-23", "5-24"], [{"name": "Pos", "value": [0.0, 75.0, 0.0, 16.666666666666668, 11.11111111111111, 0.0, 10.344827586206897]}, {"name": "Neu", "value": [100.0, 25.0, 71.42857142857143, 66.66666666666667, 88.88888888888889, 89.28571428571429, 68.96551724137932]}, {"name": "Neg", "value": [0.0, 0.0, 28.571428571428573, 16.666666666666668, 0.0, 10.714285714285714, 20.689655172413794]}]], "22": [["5-19", "5-20", "5-21", "5-22", "5-23", "5-24", "5-25"], [{"name": "Pos", "value": [75.0, 0.0, 16.666666666666668, 11.11111111111111, 0.0, 10.344827586206897, 12.0]}, {"name": "Neu", "value": [25.0, 71.42857142857143, 66.66666666666667, 88.88888888888889, 89.28571428571429, 68.96551724137932, 76.0]}, {"name": "Neg", "value": [0.0, 28.571428571428573, 16.666666666666668, 0.0, 10.714285714285714, 20.689655172413794, 12.0]}]], "23": [["5-19", "5-20", "5-21", "5-22", "5-23", "5-24", "5-25"], [{"name": "Pos", "value": [75.0, 0.0, 16.666666666666668, 11.11111111111111, 0.0, 10.344827586206897, 12.0]}, {"name": "Neu", "value": [25.0, 71.42857142857143, 66.66666666666667, 88.88888888888889, 89.28571428571429, 68.96551724137932, 76.0]}, {"name": "Neg", "value": [0.0, 28.571428571428573, 16.666666666666668, 0.0, 10.714285714285714, 20.689655172413794, 12.0]}]], "24": [["5-19", "5-20", "5-21", "5-22", "5-23", "5-24", "5-25"], [{"name": "Pos", "value": [75.0, 0.0, 16.666666666666668, 11.11111111111111, 0.0, 10.344827586206897, 12.0]}, {"name": "Neu", "value": [25.0, 71.42857142857143, 66.66666666666667, 88.88888888888889, 89.28571428571429, 68.96551724137932, 76.0]}, {"name": "Neg", "value": [0.0, 28.571428571428573, 16.666666666666668, 0.0, 10.714285714285714, 20.689655172413794, 12.0]}]], "25": [["5-19", "5-20", "5-21", "5-22", "5-23", "5-24", "5-25"], [{"name": "Pos", "value": [75.0, 0.0, 16.666666666666668, 11.11111111111111, 0.0, 10.344827586206897, 12.0]}, {"name": "Neu", "value": [25.0, 71.42857142857143, 66.66666666666667, 88.88888888888889, 89.28571428571429, 68.96551724137932, 76.0]}, {"name": "Neg", "value": [0.0, 28.571428571428573, 16.666666666666668, 0.0, 10.714285714285714, 20.689655172413794, 12.0]}]]}