{
    "安徽": {
        "累计确诊": 530,
        "新增确诊": 50,
        "累计治愈": 20,
        "新增治愈": 6,
        "累计死亡": 0,
        "新增死亡": 0
    },
    "澳门": {
        "累计确诊": 10,
        "新增确诊": 0,
        "累计治愈": 0,
        "新增治愈": 0,
        "累计死亡": 0,
        "新增死亡": 0
    },
    "福建": {
        "累计确诊": 205,
        "新增确诊": 11,
        "累计治愈": 7,
        "新增治愈": 6,
        "累计死亡": 0,
        "新增死亡": 0
    },
    "甘肃": {
        "累计确诊": 58,
        "新增确诊": 2,
        "累计治愈": 4,
        "新增治愈": 1,
        "累计死亡": 0,
        "新增死亡": 0
    },
    "广西": {
        "累计确诊": 150,
        "新增确诊": 11,
        "累计治愈": 10,
        "新增治愈": 3,
        "累计死亡": 0,
        "新增死亡": 0
    },
    "贵州": {
        "累计确诊": 64,
        "新增确诊": 8,
        "累计治愈": 5,
        "新增治愈": 3,
        "累计死亡": 0,
        "新增死亡": 0
    },
    "海南": {
        "累计确诊": 90,
        "新增确诊": 11,
        "累计治愈": 4,
        "新增治愈": 0,
        "累计死亡": 1,
        "新增死亡": 0
    },
    "河北": {
        "累计确诊": 135,
        "新增确诊": 9,
        "累计治愈": 4,
        "新增治愈": 1,
        "累计死亡": 1,
        "新增死亡": 0
    },
    "黑龙江": {
        "累计确诊": 190,
        "新增确诊": 35,
        "累计治愈": 4,
        "新增治愈": 2,
        "累计死亡": 2,
        "新增死亡": 0
    },
    "湖北": {
        "累计确诊": 16678,
        "新增确诊": 3156,
        "累计治愈": 521,
        "新增治愈": 125,
        "累计死亡": 479,
        "新增死亡": 65
    },
    "湖南": {
        "累计确诊": 661,
        "新增确诊": 68,
        "累计治愈": 35,
        "新增治愈": 13,
        "累计死亡": 0,
        "新增死亡": 0
    },
    "吉林": {
        "累计确诊": 54,
        "新增确诊": 12,
        "累计治愈": 1,
        "新增治愈": 0,
        "累计死亡": 0,
        "新增死亡": 0
    },
    "江苏": {
        "累计确诊": 341,
        "新增确诊": 33,
        "累计治愈": 13,
        "新增治愈": 5,
        "累计死亡": 0,
        "新增死亡": 0
    },
    "江西": {
        "累计确诊": 550,
        "新增确诊": 72,
        "累计治愈": 27,
        "新增治愈": 8,
        "累计死亡": 0,
        "新增死亡": 0
    },
    "辽宁": {
        "累计确诊": 81,
        "新增确诊": 7,
        "累计治愈": 2,
        "新增治愈": 1,
        "累计死亡": 0,
        "新增死亡": 0
    },
    "内蒙古": {
        "累计确诊": 42,
        "新增确诊": 7,
        "累计治愈": 1,
        "新增治愈": 0,
        "累计死亡": 0,
        "新增死亡": 0
    },
    "宁夏": {
        "累计确诊": 34,
        "新增确诊": 0,
        "累计治愈": 1,
        "新增治愈": 0,
        "累计死亡": 0,
        "新增死亡": 0
    },
    "青海": {
        "累计确诊": 17,
        "新增确诊": 2,
        "累计治愈": 0,
        "新增治愈": 0,
        "累计死亡": 0,
        "新增死亡": 0
    },
    "山东": {
        "累计确诊": 298,
        "新增确诊": 28,
        "累计治愈": 13,
        "新增治愈": 6,
        "累计死亡": 0,
        "新增死亡": 0
    },
    "山西": {
        "累计确诊": 81,
        "新增确诊": 7,
        "累计治愈": 4,
        "新增治愈": 2,
        "累计死亡": 0,
        "新增死亡": 0
    },
    "陕西": {
        "累计确诊": 166,
        "新增确诊": 23,
        "累计治愈": 2,
        "新增治愈": 1,
        "累计死亡": 0,
        "新增死亡": 0
    },
    "上海": {
        "累计确诊": 233,
        "新增确诊": 25,
        "累计治愈": 12,
        "新增治愈": 2,
        "累计死亡": 1,
        "新增死亡": 0
    },
    "四川": {
        "累计确诊": 302,
        "新增确诊": 19,
        "累计治愈": 23,
        "新增治愈": 9,
        "累计死亡": 1,
        "新增死亡": 0
    },
    "台湾": {
        "累计确诊": 11,
        "新增确诊": 1,
        "累计治愈": 0,
        "新增治愈": 0,
        "累计死亡": 0,
        "新增死亡": 0
    },
    "天津": {
        "累计确诊": 67,
        "新增确诊": 7,
        "累计治愈": 2,
        "新增治愈": 1,
        "累计死亡": 0,
        "新增死亡": 0
    },
    "西藏": {
        "累计确诊": 1,
        "新增确诊": 0,
        "累计治愈": 0,
        "新增治愈": 0,
        "累计死亡": 0,
        "新增死亡": 0
    },
    "香港": {
        "累计确诊": 18,
        "新增确诊": 3,
        "累计治愈": 0,
        "新增治愈": 0,
        "累计死亡": 1,
        "新增死亡": 1
    },
    "新疆": {
        "累计确诊": 32,
        "新增确诊": 3,
        "累计治愈": 0,
        "新增治愈": 0,
        "累计死亡": 0,
        "新增死亡": 0
    },
    "云南": {
        "累计确诊": 122,
        "新增确诊": 5,
        "累计治愈": 5,
        "新增治愈": 0,
        "累计死亡": 0,
        "新增死亡": 0
    },
    "浙江": {
        "累计确诊": 895,
        "新增确诊": 66,
        "累计治愈": 63,
        "新增治愈": 15,
        "累计死亡": 0,
        "新增死亡": 0
    },
    "重庆": {
        "累计确诊": 366,
        "新增确诊": 29,
        "累计治愈": 14,
        "新增治愈": 5,
        "累计死亡": 2,
        "新增死亡": 0
    },
    "北京": {
        "累计确诊": 259,
        "新增确诊": 25,
        "累计治愈": 24,
        "新增治愈": 1,
        "累计死亡": 1,
        "新增死亡": 0
    },
    "河南": {
        "累计确诊": 764,
        "新增确诊": 89,
        "累计治愈": 41,
        "新增治愈": 21,
        "累计死亡": 2,
        "新增死亡": 0
    },
    "广东": {
        "累计确诊": 870,
        "新增确诊": 73,
        "累计治愈": 32,
        "新增治愈": 12,
        "累计死亡": 0,
        "新增死亡": 0
    }
}